pypykatz/__init__.py
pypykatz/apypykatz.py
pypykatz/pypykatz.py
pypykatz/alsadecryptor/__init__.py
pypykatz/alsadecryptor/asbmfile.py
pypykatz/alsadecryptor/lsa_decryptor.py
pypykatz/alsadecryptor/lsa_decryptor_nt5.py
pypykatz/alsadecryptor/lsa_decryptor_nt6.py
pypykatz/alsadecryptor/lsa_template_nt5.py
pypykatz/alsadecryptor/lsa_template_nt6.py
pypykatz/alsadecryptor/lsa_templates.py
pypykatz/alsadecryptor/package_commons.py
pypykatz/alsadecryptor/win_datatypes.py
pypykatz/alsadecryptor/packages/__init__.py
pypykatz/alsadecryptor/packages/cloudap/__init__.py
pypykatz/alsadecryptor/packages/cloudap/decryptor.py
pypykatz/alsadecryptor/packages/cloudap/templates.py
pypykatz/alsadecryptor/packages/credman/__init__.py
pypykatz/alsadecryptor/packages/credman/templates.py
pypykatz/alsadecryptor/packages/dpapi/__init__.py
pypykatz/alsadecryptor/packages/dpapi/decryptor.py
pypykatz/alsadecryptor/packages/dpapi/templates.py
pypykatz/alsadecryptor/packages/kerberos/__init__.py
pypykatz/alsadecryptor/packages/kerberos/decryptor.py
pypykatz/alsadecryptor/packages/kerberos/templates.py
pypykatz/alsadecryptor/packages/livessp/__init__.py
pypykatz/alsadecryptor/packages/livessp/decryptor.py
pypykatz/alsadecryptor/packages/livessp/templates.py
pypykatz/alsadecryptor/packages/msv/__init__.py
pypykatz/alsadecryptor/packages/msv/decryptor.py
pypykatz/alsadecryptor/packages/msv/templates.py
pypykatz/alsadecryptor/packages/ssp/__init__.py
pypykatz/alsadecryptor/packages/ssp/decryptor.py
pypykatz/alsadecryptor/packages/ssp/templates.py
pypykatz/alsadecryptor/packages/tspkg/__init__.py
pypykatz/alsadecryptor/packages/tspkg/decryptor.py
pypykatz/alsadecryptor/packages/tspkg/templates.py
pypykatz/alsadecryptor/packages/wdigest/__init__.py
pypykatz/alsadecryptor/packages/wdigest/decryptor.py
pypykatz/alsadecryptor/packages/wdigest/templates.py
pypykatz/commons/__init__.py
pypykatz/commons/common.py
pypykatz/commons/filetime.py
pypykatz/commons/kerberosticket.py
dprdp-0.1.2.dist-info/METADATA
dprdp-0.1.2.dist-info/WHEEL
dprdp-0.1.2.dist-info/top_level.txt
dprdp-0.1.2.dist-info/RECORD
